nsut/__init__.py
nsut/__main__.py
nsut/notice_scraper.py
nsut-0.0.1.dist-info/METADATA
nsut-0.0.1.dist-info/WHEEL
nsut-0.0.1.dist-info/dependency_links.txt
nsut-0.0.1.dist-info/entry_points.txt
nsut-0.0.1.dist-info/top_level.txt
nsut-0.0.1.dist-info/RECORD
