Metadata-Version: 2.1
Name: nsut
Version: 0.0.1
Summary: A simple Command Line Interface to access NSUT's IMS Notices
Home-page: https://github.com/param211/nsut
Author: Param Chauhan
Author-email: paramchauhan21@gmail.com
License: MIT
Download-URL: https://github.com/param211/nsut/archive/0.0.1.tar.gz
Platform: UNKNOWN
Classifier: License :: OSI Approved :: MIT License
Classifier: Programming Language :: Python :: 3
Classifier: Programming Language :: Python :: 3.8
Requires-Python: >=3.0
Requires-Dist: beautifulsoup4 (==4.9.3)
Requires-Dist: certifi (==2020.12.5)
Requires-Dist: chardet (==4.0.0)
Requires-Dist: click (==7.1.2)
Requires-Dist: colorama (==0.4.4)
Requires-Dist: commonmark (==0.9.1)
Requires-Dist: idna (==2.10)
Requires-Dist: Pygments (==2.8.0)
Requires-Dist: requests (==2.25.1)
Requires-Dist: rich (==9.12.4)
Requires-Dist: soupsieve (==2.2)
Requires-Dist: typing-extensions (==3.7.4.3)
Requires-Dist: urllib3 (==1.26.3)
